cosinnus_poll/__init__.py
cosinnus_poll/admin.py
cosinnus_poll/apps.py
cosinnus_poll/conf.py
cosinnus_poll/cosinnus_app.py
cosinnus_poll/cosinnus_notifications.py
cosinnus_poll/dashboard.py
cosinnus_poll/filters.py
cosinnus_poll/forms.py
cosinnus_poll/managers.py
cosinnus_poll/models.py
cosinnus_poll/notify.py
cosinnus_poll/search_indexes.py
cosinnus_poll/urls.py
cosinnus_poll/views.py
cosinnus_poll/locale/de/LC_MESSAGES/django.mo
cosinnus_poll/locale/de/LC_MESSAGES/django.po
cosinnus_poll/locale/en/LC_MESSAGES/django.mo
cosinnus_poll/locale/en/LC_MESSAGES/django.po
cosinnus_poll/locale/fr/LC_MESSAGES/django.mo
cosinnus_poll/locale/fr/LC_MESSAGES/django.po
cosinnus_poll/locale/ru/LC_MESSAGES/django.mo
cosinnus_poll/locale/ru/LC_MESSAGES/django.po
cosinnus_poll/locale/uk/LC_MESSAGES/django.mo
cosinnus_poll/locale/uk/LC_MESSAGES/django.po
cosinnus_poll/migrations/0001_initial.py
cosinnus_poll/migrations/0002_auto_20160705_1323.py
cosinnus_poll/migrations/0003_poll_show_voters.py
cosinnus_poll/migrations/__init__.py
cosinnus_poll/static/css/cosinnus_poll/cosinnus_poll.css
cosinnus_poll/static/js/cosinnus_poll/cosinnus_poll.js
cosinnus_poll/static/js/vendor/bootstrap.inline.js
cosinnus_poll/templates/cosinnus_poll/attached_object_select_pill.html
cosinnus_poll/templates/cosinnus_poll/attached_polls.html
cosinnus_poll/templates/cosinnus_poll/base.html
cosinnus_poll/templates/cosinnus_poll/inlineform_poll_choices_content.html
cosinnus_poll/templates/cosinnus_poll/leftnav.html
cosinnus_poll/templates/cosinnus_poll/list_object.html
cosinnus_poll/templates/cosinnus_poll/poll_comments.html
cosinnus_poll/templates/cosinnus_poll/poll_form.html
cosinnus_poll/templates/cosinnus_poll/poll_list.html
cosinnus_poll/templates/cosinnus_poll/poll_list_standalone.html
cosinnus_poll/templates/cosinnus_poll/poll_vote.html
cosinnus_poll/templates/cosinnus_poll/poll_vote_avatar.html
cosinnus_poll/templates/cosinnus_poll/single_poll.html
cosinnus_poll-0.1.dev20180515152632.dist-info/DESCRIPTION.rst
cosinnus_poll-0.1.dev20180515152632.dist-info/METADATA
cosinnus_poll-0.1.dev20180515152632.dist-info/RECORD
cosinnus_poll-0.1.dev20180515152632.dist-info/WHEEL
cosinnus_poll-0.1.dev20180515152632.dist-info/metadata.json
cosinnus_poll-0.1.dev20180515152632.dist-info/top_level.txt
